Metadata-Version: 2.1
Name: odoo-addon-account_move_line_mrp_info
Version: 18.0.1.0.0.5
Requires-Python: >=3.10
Requires-Dist: odoo-addon-account_move_line_stock_info==18.0.*
Requires-Dist: odoo==18.0.*
Summary: Account Move Line Mrp Info
Home-page: https://github.com/OCA/manufacture
License: AGPL-3
Author: ForgeFlow,Odoo Community Association (OCA)
Author-email: support@odoo-community.org
Classifier: Programming Language :: Python
Classifier: Framework :: Odoo
Classifier: Framework :: Odoo :: 18.0
Classifier: License :: OSI Approved :: GNU Affero General Public License v3
